[
  {
    "Author": "Kaciexx, Aspher0",
    "Name": "FFXIV Vibe Plugin",
    "Description": "Plugin that let you vibe your controller or toys.",
    "InternalName": "FFXIV_Vibe_Plugin",
    "AssemblyVersion": "3.2.0.0",
    "RepoUrl": "https://github.com/Aspher0/FFXIV_Vibe_Plugin",
    "ApplicableVersion": "any",
    "Tags": [
      "vibe",
      "vibration",
      "wave"
    ],
    "DalamudApiLevel": 12,
    "IconUrl": "https://github.com/Aspher0/FFXIV_Vibe_Plugin/raw/master/images/icon.png",
    "IsHide": "False",
    "IsTestingExclusive": "False",
    "DownloadCount": 10900,
    "DownloadLinkInstall": "https://github.com/Aspher0/FFXIV_Vibe_Plugin/releases/download/v3.2.0.0/latest.zip",
    "DownloadLinkTesting": "https://github.com/Aspher0/FFXIV_Vibe_Plugin/releases/download/v3.2.0.0/latest.zip",
    "DownloadLinkUpdate": "https://github.com/Aspher0/FFXIV_Vibe_Plugin/releases/download/v3.2.0.0/latest.zip"
  }
]
